MANIFEST.in
README.rst
setup.py
python_valve.egg-info/PKG-INFO
python_valve.egg-info/SOURCES.txt
python_valve.egg-info/dependency_links.txt
python_valve.egg-info/requires.txt
python_valve.egg-info/top_level.txt
valve/__init__.py
valve/rcon.py
valve/testing.py
valve/uni.py
valve/vdf.py
valve/source/__init__.py
valve/source/a2s.py
valve/source/master_server.py
valve/source/messages.py
valve/source/util.py
valve/steam/__init__.py
valve/steam/client.py
valve/steam/id.py
valve/steam/api/__init__.py
valve/steam/api/interface.py