Metadata-Version: 1.1
Name: python-valve
Version: 0.2.1
Summary: Python implementation for Source servers, RCON, A2S, VDF, the Steam Web API and various other Valve products and services.
Home-page: https://github.com/serverstf/python-valve
Author: Oliver Ainsworth
Author-email: ottajay@googlemail.com
License: MIT License
Platform: UNKNOWN
Classifier: Development Status :: 4 - Beta
Classifier: Intended Audience :: Developers
Classifier: License :: OSI Approved :: MIT License
Classifier: Programming Language :: Python :: 2.7
Classifier: Programming Language :: Python :: 3.4
Classifier: Programming Language :: Python :: 3.5
Classifier: Programming Language :: Python :: 3.6
Classifier: Programming Language :: Python :: 3.7
Classifier: Programming Language :: Python :: Implementation :: CPython
Classifier: Programming Language :: Python :: Implementation :: PyPy
Classifier: Topic :: Games/Entertainment
